{
  "number" : 15,
  "tanks" : [ {
    "name" : "Artur",
    "color" : "0xa7531e",
    "hp" : 100,
    "position" : {
      "x" : 356.14,
      "y" : 75.62
    },
    "alive" : true
  }, {
    "name" : "choke",
    "color" : "0xed1569",
    "hp" : 100,
    "position" : {
      "x" : 116.43,
      "y" : 133.75
    },
    "alive" : true
  }, {
    "name" : "MarcinS",
    "color" : "0x851a6f",
    "hp" : 100,
    "position" : {
      "x" : -345.14,
      "y" : 55.46
    },
    "alive" : true
  }, {
    "name" : "TARS",
    "color" : "0xe44118",
    "hp" : 100,
    "position" : {
      "x" : 205.29,
      "y" : 173.87
    },
    "alive" : true
  }, {
    "name" : "tankus",
    "color" : "0x8fb8f5",
    "hp" : 100,
    "position" : {
      "x" : -108.43,
      "y" : 54.61
    },
    "alive" : true
  } ],
  "outcome" : [ {
    "name" : "Artur",
    "color" : "0xa7531e",
    "type" : "ground_hit",
    "hitCoordinates" : {
      "x" : 277.11,
      "y" : 172.62
    },
    "target" : null,
    "targetDestroyed" : false,
    "bulletTrajectory" : [ {
      "x" : 356.14,
      "y" : 85.62
    }, {
      "x" : 359.59,
      "y" : 125.75
    }, {
      "x" : 362.64,
      "y" : 161.97
    }, {
      "x" : 365.34,
      "y" : 194.86
    }, {
      "x" : 367.74,
      "y" : 224.87
    }, {
      "x" : 369.87,
      "y" : 252.37
    }, {
      "x" : 371.75,
      "y" : 277.62
    }, {
      "x" : 373.41,
      "y" : 300.87
    }, {
      "x" : 374.86,
      "y" : 322.3
    }, {
      "x" : 376.12,
      "y" : 342.07
    }, {
      "x" : 377.2,
      "y" : 360.3
    }, {
      "x" : 378.1,
      "y" : 377.12
    }, {
      "x" : 378.85,
      "y" : 392.62
    }, {
      "x" : 379.43,
      "y" : 406.87
    }, {
      "x" : 379.87,
      "y" : 419.96
    }, {
      "x" : 380.15,
      "y" : 431.93
    }, {
      "x" : 380.3,
      "y" : 442.84
    }, {
      "x" : 380.31,
      "y" : 452.74
    }, {
      "x" : 380.18,
      "y" : 461.66
    }, {
      "x" : 379.91,
      "y" : 469.64
    }, {
      "x" : 379.52,
      "y" : 476.71
    }, {
      "x" : 378.99,
      "y" : 482.89
    }, {
      "x" : 378.33,
      "y" : 488.2
    }, {
      "x" : 377.54,
      "y" : 492.66
    }, {
      "x" : 376.61,
      "y" : 496.28
    }, {
      "x" : 375.56,
      "y" : 499.07
    }, {
      "x" : 374.37,
      "y" : 501.05
    }, {
      "x" : 373.04,
      "y" : 502.21
    }, {
      "x" : 371.58,
      "y" : 502.56
    }, {
      "x" : 369.99,
      "y" : 502.11
    }, {
      "x" : 368.27,
      "y" : 500.84
    }, {
      "x" : 366.42,
      "y" : 498.78
    }, {
      "x" : 364.44,
      "y" : 495.93
    }, {
      "x" : 362.34,
      "y" : 492.3
    }, {
      "x" : 360.13,
      "y" : 487.91
    }, {
      "x" : 357.8,
      "y" : 482.76
    }, {
      "x" : 355.37,
      "y" : 476.88
    }, {
      "x" : 352.84,
      "y" : 470.29
    }, {
      "x" : 350.2,
      "y" : 463
    }, {
      "x" : 347.48,
      "y" : 455.05
    }, {
      "x" : 344.67,
      "y" : 446.44
    }, {
      "x" : 341.78,
      "y" : 437.21
    }, {
      "x" : 338.82,
      "y" : 427.38
    }, {
      "x" : 335.78,
      "y" : 416.98
    }, {
      "x" : 332.68,
      "y" : 406.02
    }, {
      "x" : 329.52,
      "y" : 394.55
    }, {
      "x" : 326.31,
      "y" : 382.58
    }, {
      "x" : 323.04,
      "y" : 370.13
    }, {
      "x" : 319.73,
      "y" : 357.24
    }, {
      "x" : 316.38,
      "y" : 343.92
    }, {
      "x" : 312.99,
      "y" : 330.21
    }, {
      "x" : 309.57,
      "y" : 316.12
    }, {
      "x" : 306.11,
      "y" : 301.68
    }, {
      "x" : 302.64,
      "y" : 286.9
    }, {
      "x" : 299.13,
      "y" : 271.81
    }, {
      "x" : 295.61,
      "y" : 256.43
    }, {
      "x" : 292.07,
      "y" : 240.78
    }, {
      "x" : 288.52,
      "y" : 224.88
    }, {
      "x" : 284.95,
      "y" : 208.74
    }, {
      "x" : 281.38,
      "y" : 192.37
    }, {
      "x" : 277.79,
      "y" : 175.8
    }, {
      "x" : 277.11,
      "y" : 172.62
    } ],
    "tankMovement" : [ {
      "x" : 356.14,
      "y" : 75.62
    } ]
  }, {
    "name" : "choke",
    "color" : "0xed1569",
    "type" : "ground_hit",
    "hitCoordinates" : {
      "x" : 48.69,
      "y" : 132.84
    },
    "target" : null,
    "targetDestroyed" : false,
    "bulletTrajectory" : [ {
      "x" : 116.43,
      "y" : 143.75
    }, {
      "x" : 111.58,
      "y" : 147.67
    }, {
      "x" : 106.65,
      "y" : 150.73
    }, {
      "x" : 101.64,
      "y" : 152.96
    }, {
      "x" : 96.54,
      "y" : 154.37
    }, {
      "x" : 91.36,
      "y" : 154.96
    }, {
      "x" : 86.1,
      "y" : 154.74
    }, {
      "x" : 80.76,
      "y" : 153.73
    }, {
      "x" : 75.34,
      "y" : 151.92
    }, {
      "x" : 69.85,
      "y" : 149.34
    }, {
      "x" : 64.3,
      "y" : 145.99
    }, {
      "x" : 58.69,
      "y" : 141.89
    }, {
      "x" : 53.02,
      "y" : 137.05
    }, {
      "x" : 48.69,
      "y" : 132.84
    } ],
    "tankMovement" : [ {
      "x" : 116.43,
      "y" : 133.75
    } ]
  }, {
    "name" : "TARS",
    "color" : "0xe44118",
    "type" : "ground_hit",
    "hitCoordinates" : {
      "x" : -301.78,
      "y" : 53.7
    },
    "target" : null,
    "targetDestroyed" : false,
    "bulletTrajectory" : [ {
      "x" : 205.29,
      "y" : 183.87
    }, {
      "x" : 165.33,
      "y" : 183.13
    }, {
      "x" : 128.46,
      "y" : 181.7
    }, {
      "x" : 94.19,
      "y" : 179.64
    }, {
      "x" : 62.16,
      "y" : 176.95
    }, {
      "x" : 32.07,
      "y" : 173.69
    }, {
      "x" : 3.69,
      "y" : 169.86
    }, {
      "x" : -23.19,
      "y" : 165.5
    }, {
      "x" : -48.71,
      "y" : 160.6
    }, {
      "x" : -73.03,
      "y" : 155.2
    }, {
      "x" : -96.25,
      "y" : 149.3
    }, {
      "x" : -118.48,
      "y" : 142.92
    }, {
      "x" : -139.79,
      "y" : 136.06
    }, {
      "x" : -160.26,
      "y" : 128.75
    }, {
      "x" : -179.96,
      "y" : 120.98
    }, {
      "x" : -198.94,
      "y" : 112.77
    }, {
      "x" : -217.25,
      "y" : 104.14
    }, {
      "x" : -234.94,
      "y" : 95.09
    }, {
      "x" : -252.04,
      "y" : 85.63
    }, {
      "x" : -268.58,
      "y" : 75.77
    }, {
      "x" : -284.6,
      "y" : 65.52
    }, {
      "x" : -300.13,
      "y" : 54.9
    }, {
      "x" : -301.78,
      "y" : 53.7
    } ],
    "tankMovement" : [ {
      "x" : 205.29,
      "y" : 173.87
    } ]
  }, {
    "name" : "MarcinS",
    "color" : "0x851a6f",
    "type" : "ground_hit",
    "hitCoordinates" : {
      "x" : -265.98,
      "y" : 68.06
    },
    "target" : null,
    "targetDestroyed" : false,
    "bulletTrajectory" : [ {
      "x" : -345.14,
      "y" : 65.46
    }, {
      "x" : -338.41,
      "y" : 71.53
    }, {
      "x" : -331.92,
      "y" : 76.71
    }, {
      "x" : -325.68,
      "y" : 81.01
    }, {
      "x" : -319.65,
      "y" : 84.45
    }, {
      "x" : -313.84,
      "y" : 87.05
    }, {
      "x" : -308.24,
      "y" : 88.81
    }, {
      "x" : -302.84,
      "y" : 89.76
    }, {
      "x" : -297.63,
      "y" : 89.89
    }, {
      "x" : -292.61,
      "y" : 89.22
    }, {
      "x" : -287.78,
      "y" : 87.76
    }, {
      "x" : -283.14,
      "y" : 85.51
    }, {
      "x" : -278.69,
      "y" : 82.48
    }, {
      "x" : -274.42,
      "y" : 78.69
    }, {
      "x" : -270.35,
      "y" : 74.14
    }, {
      "x" : -266.46,
      "y" : 68.86
    }, {
      "x" : -265.98,
      "y" : 68.06
    } ],
    "tankMovement" : [ {
      "x" : -345.14,
      "y" : 55.46
    } ]
  }, {
    "name" : "tankus",
    "color" : "0x8fb8f5",
    "type" : "ground_hit",
    "hitCoordinates" : {
      "x" : -253.59,
      "y" : 71.77
    },
    "target" : null,
    "targetDestroyed" : false,
    "bulletTrajectory" : [ {
      "x" : -108.43,
      "y" : 64.61
    }, {
      "x" : -108,
      "y" : 95.77
    }, {
      "x" : -107.73,
      "y" : 124.27
    }, {
      "x" : -107.61,
      "y" : 150.43
    }, {
      "x" : -107.62,
      "y" : 174.5
    }, {
      "x" : -107.76,
      "y" : 196.67
    }, {
      "x" : -108.03,
      "y" : 217.12
    }, {
      "x" : -108.43,
      "y" : 235.99
    }, {
      "x" : -108.94,
      "y" : 253.39
    }, {
      "x" : -109.57,
      "y" : 269.44
    }, {
      "x" : -110.32,
      "y" : 284.21
    }, {
      "x" : -111.18,
      "y" : 297.78
    }, {
      "x" : -112.16,
      "y" : 310.21
    }, {
      "x" : -113.24,
      "y" : 321.56
    }, {
      "x" : -114.44,
      "y" : 331.88
    }, {
      "x" : -115.75,
      "y" : 341.2
    }, {
      "x" : -117.18,
      "y" : 349.57
    }, {
      "x" : -118.72,
      "y" : 357.01
    }, {
      "x" : -120.38,
      "y" : 363.55
    }, {
      "x" : -122.15,
      "y" : 369.22
    }, {
      "x" : -124.05,
      "y" : 374.02
    }, {
      "x" : -126.06,
      "y" : 377.97
    }, {
      "x" : -128.19,
      "y" : 381.09
    }, {
      "x" : -130.46,
      "y" : 383.39
    }, {
      "x" : -132.84,
      "y" : 384.87
    }, {
      "x" : -135.35,
      "y" : 385.53
    }, {
      "x" : -137.99,
      "y" : 385.39
    }, {
      "x" : -140.75,
      "y" : 384.44
    }, {
      "x" : -143.62,
      "y" : 382.69
    }, {
      "x" : -146.62,
      "y" : 380.15
    }, {
      "x" : -149.72,
      "y" : 376.84
    }, {
      "x" : -152.93,
      "y" : 372.76
    }, {
      "x" : -156.23,
      "y" : 367.92
    }, {
      "x" : -159.63,
      "y" : 362.35
    }, {
      "x" : -163.12,
      "y" : 356.06
    }, {
      "x" : -166.69,
      "y" : 349.08
    }, {
      "x" : -170.33,
      "y" : 341.42
    }, {
      "x" : -174.04,
      "y" : 333.11
    }, {
      "x" : -177.82,
      "y" : 324.17
    }, {
      "x" : -181.65,
      "y" : 314.62
    }, {
      "x" : -185.53,
      "y" : 304.49
    }, {
      "x" : -189.46,
      "y" : 293.81
    }, {
      "x" : -193.42,
      "y" : 282.6
    }, {
      "x" : -197.43,
      "y" : 270.88
    }, {
      "x" : -201.46,
      "y" : 258.69
    }, {
      "x" : -205.51,
      "y" : 246.03
    }, {
      "x" : -209.59,
      "y" : 232.95
    }, {
      "x" : -213.68,
      "y" : 219.47
    }, {
      "x" : -217.79,
      "y" : 205.59
    }, {
      "x" : -221.9,
      "y" : 191.36
    }, {
      "x" : -226.02,
      "y" : 176.79
    }, {
      "x" : -230.14,
      "y" : 161.9
    }, {
      "x" : -234.27,
      "y" : 146.71
    }, {
      "x" : -238.39,
      "y" : 131.24
    }, {
      "x" : -242.5,
      "y" : 115.5
    }, {
      "x" : -246.61,
      "y" : 99.53
    }, {
      "x" : -250.72,
      "y" : 83.32
    }, {
      "x" : -253.59,
      "y" : 71.77
    } ],
    "tankMovement" : [ {
      "x" : -108.43,
      "y" : 54.61
    } ]
  } ],
  "last" : false
}